setup.py
deepSeg.egg-info/PKG-INFO
deepSeg.egg-info/SOURCES.txt
deepSeg.egg-info/dependency_links.txt
deepSeg.egg-info/requires.txt
deepSeg.egg-info/top_level.txt
deepseg/__init__.py
deepseg/deepseg.py
deepseg/deepseg_util.py
deepseg/model/as_dict.json
deepseg/model/as_model.json
tests/__init__.py
tests/test_deepseg.py
tests/test_deepseg_util.py