Metadata-Version: 1.0
Name: deepSeg
Version: 0.0.1
Summary: A deep learning Chinese Word Segmentation toolkit
Home-page: UNKNOWN
Author: ckmarkoh
Author-email: ckmarkoh@gmail.com
License: UNKNOWN
Platform: UNKNOWN
